acme_test_01/__init__.py
acme_test_01/validator.py
acme_test_01-0.1.0.dist-info/METADATA
acme_test_01-0.1.0.dist-info/WHEEL
acme_test_01-0.1.0.dist-info/RECORD
